bay_area_mashers_member_export/__init__.py
bay_area_mashers_member_export-1.0.0.dist-info/METADATA
bay_area_mashers_member_export-1.0.0.dist-info/WHEEL
bay_area_mashers_member_export-1.0.0.dist-info/entry_points.txt
bay_area_mashers_member_export-1.0.0.dist-info/top_level.txt
bay_area_mashers_member_export-1.0.0.dist-info/RECORD
