Metadata-Version: 2.1
Name: bay-area-mashers-member-export
Version: 1.0.0
Summary: Tool to query Bay Area Mashers member list and return all current members' email addresses
Home-page: https://github.com/bay-area-mashers/bay-area-mashers-member-export
Author: Gene Wood
Author-email: gene_wood@cementhorizon.com
License: GPL-3.0
Platform: UNKNOWN
Requires-Dist: gspread
